metdig/__init__.py
metdig/package_tools.py
metdig/__pycache__/__init__.cpython-38.pyc
metdig/__pycache__/__init__.cpython-39.pyc
metdig/__pycache__/package_tools.cpython-38.pyc
metdig/__pycache__/package_tools.cpython-39.pyc
metdig/cal/__init__.py
metdig/cal/classification.py
metdig/cal/cross_sections_module.py
metdig/cal/dynamic.py
metdig/cal/elements.py
metdig/cal/ensemble.py
metdig/cal/extreme.py
metdig/cal/identify.py
metdig/cal/indexes.py
metdig/cal/interpolate.py
metdig/cal/metpy_cal.py
metdig/cal/moisture.py
metdig/cal/other.py
metdig/cal/qpf.py
metdig/cal/sounding.py
metdig/cal/thermal.py
metdig/cal/tools.py
metdig/cal/__pycache__/__init__.cpython-38.pyc
metdig/cal/__pycache__/__init__.cpython-39.pyc
metdig/cal/__pycache__/classification.cpython-38.pyc
metdig/cal/__pycache__/classification.cpython-39.pyc
metdig/cal/__pycache__/cross_sections_module.cpython-38.pyc
metdig/cal/__pycache__/cross_sections_module.cpython-39.pyc
metdig/cal/__pycache__/dynamic.cpython-38.pyc
metdig/cal/__pycache__/dynamic.cpython-39.pyc
metdig/cal/__pycache__/elements.cpython-38.pyc
metdig/cal/__pycache__/elements.cpython-39.pyc
metdig/cal/__pycache__/ensemble.cpython-38.pyc
metdig/cal/__pycache__/ensemble.cpython-39.pyc
metdig/cal/__pycache__/extreme.cpython-38.pyc
metdig/cal/__pycache__/extreme.cpython-39.pyc
metdig/cal/__pycache__/identify.cpython-38.pyc
metdig/cal/__pycache__/identify.cpython-39.pyc
metdig/cal/__pycache__/indexes.cpython-38.pyc
metdig/cal/__pycache__/indexes.cpython-39.pyc
metdig/cal/__pycache__/interpolate.cpython-38.pyc
metdig/cal/__pycache__/interpolate.cpython-39.pyc
metdig/cal/__pycache__/moisture.cpython-38.pyc
metdig/cal/__pycache__/moisture.cpython-39.pyc
metdig/cal/__pycache__/other.cpython-38.pyc
metdig/cal/__pycache__/other.cpython-39.pyc
metdig/cal/__pycache__/qpf.cpython-38.pyc
metdig/cal/__pycache__/qpf.cpython-39.pyc
metdig/cal/__pycache__/sounding.cpython-38.pyc
metdig/cal/__pycache__/sounding.cpython-39.pyc
metdig-1.0.7.3.dist-info/LICENSE
metdig-1.0.7.3.dist-info/METADATA
metdig-1.0.7.3.dist-info/WHEEL
metdig-1.0.7.3.dist-info/top_level.txt
metdig-1.0.7.3.dist-info/RECORD
